myuploadtest/__init__.py
myuploadtest/test.py
myuploadtest-0.1.0.dist-info/METADATA
myuploadtest-0.1.0.dist-info/WHEEL
myuploadtest-0.1.0.dist-info/top_level.txt
myuploadtest-0.1.0.dist-info/RECORD
