Metadata-Version: 2.1
Name: myuploadtest
Version: 0.1.0
Summary: test pip upload
Home-page: 
Author: lily
Author-email: 2239041944@qq.com
License: MIT
